[{"id":1,"username":"Абдгании","phonenumber":"998997811356","birthday":"2003-06-02","erkakAyol":"erkak","telegram":"@abduganii","cursname":"Backend","cotegoriId":2,"password":"8d13037"},{"id":2,"username":"Komil","phonenumber":"998945562134","birthday":"2022-02-03","erkakAyol":"erkak","telegram":"@komil_87","cursname":"node.js","cotegoriId":2,"password":"5m22715"},{"id":3,"username":"Ali","phonenumber":"998997865467","birthday":"2022-02-11","erkakAyol":"erkak","telegram":"@Ali","cursname":"Fron-end","cotegoriId":2,"password":"8i39402"},{"id":4,"username":"aaaaaa","phonenumber":"87860060065","birthday":"2021-12-25","erkakAyol":"ayol","telegram":"@alisher_22","cursname":"node.js","cotegoriId":2,"password":"6i47765"}]